[{"score": 1, "chord_style": "standard", "progression_style": "pop", "duplicate_id": 184, "style": "pop_standard", "cycle": [1.0, 32], "pattern": "unknown", "position": null, "rhythm": "unknown", "progression": [["F 0"], ["G 0"], ["A 1"], ["C 0"], ["F 0"], ["G 0"], ["A 1"], ["C 0"]], "other_possible_styles": ["pop_standard", "pop_complex"]}, {"score": 1, "chord_style": "standard", "progression_style": "pop", "duplicate_id": 184, "style": "pop_standard", "cycle": [1.0, 32], "pattern": "unknown", "position": null, "rhythm": "unknown", "progression": [["E 0"], ["F#0"], ["G#1"], ["B 0"], ["E 0"], ["F#0"], ["G#1"], ["B 0"]], "other_possible_styles": ["pop_standard", "pop_complex"]}, {"score": 1, "chord_style": "standard", "progression_style": "pop", "duplicate_id": 180, "style": "pop_standard", "cycle": [1.0, 32], "pattern": "unknown", "position": null, "rhythm": "unknown", "progression": [["G#1"], ["B 0"], ["E 0"], ["F#0"], ["G#1"], ["B 0"], ["E 0"], ["F#0"]], "other_possible_styles": ["pop_standard", "pop_complex"]}, {"score": 1, "chord_style": "standard", "progression_style": "edm", "duplicate_id": 176, "style": "pop_standard", "cycle": [1.0, 32], "pattern": "unknown", "position": null, "rhythm": "unknown", "progression": [["F 0"], ["C 0"], ["D 1"], ["Bb0"], ["F 0"], ["C 0"], ["D 1"], ["Bb0"]], "other_possible_styles": ["pop_standard", "pop_complex"]}, {"score": 1, "chord_style": "standard", "progression_style": "edm", "duplicate_id": 176, "style": "pop_standard", "cycle": [1.0, 32], "pattern": "unknown", "position": null, "rhythm": "unknown", "progression": [["C 0"], ["G 0"], ["A 1"], ["F 0"], ["C 0"], ["G 0"], ["A 1"], ["F 0"]], "other_possible_styles": ["pop_standard", "pop_complex"]}, {"score": 1, "chord_style": "standard", "progression_style": "pop", "duplicate_id": 151, "style": "pop_standard", "cycle": [1.0, 32], "pattern": "unknown", "position": null, "rhythm": "unknown", "progression": [["Eb0"], ["C 1"], ["Ab0"], ["Bb0"], ["Eb0"], ["C 1"], ["Ab0"], ["Bb0"]], "other_possible_styles": ["pop_standard", "pop_complex"]}]